{
  "elements": [
    {
      "element": {
        "element_type": "minecraft:single_pool_element",
        "location": "landsoficaria:villages/scrubland/ruined/street",
        "processors": {
          "processors": []
        },
        "projection": "terrain_matching"
      },
      "weight": 4
    },
    {
      "element": {
        "element_type": "minecraft:single_pool_element",
        "location": "landsoficaria:villages/scrubland/ruined/street_stop",
        "processors": {
          "processors": []
        },
        "projection": "terrain_matching"
      },
      "weight": 1
    },
    {
      "element": {
        "element_type": "minecraft:single_pool_element",
        "location": "landsoficaria:villages/scrubland/ruined/street_stop_arch",
        "processors": {
          "processors": []
        },
        "projection": "terrain_matching"
      },
      "weight": 1
    },
    {
      "element": {
        "element_type": "minecraft:single_pool_element",
        "location": "landsoficaria:villages/scrubland/ruined/street_stop_junc",
        "processors": {
          "processors": []
        },
        "projection": "terrain_matching"
      },
      "weight": 1
    },
    {
      "element": {
        "element_type": "minecraft:single_pool_element",
        "location": "landsoficaria:villages/scrubland/ruined/street_stop_long",
        "processors": {
          "processors": []
        },
        "projection": "terrain_matching"
      },
      "weight": 1
    },
    {
      "element": {
        "element_type": "minecraft:single_pool_element",
        "location": "landsoficaria:villages/scrubland/ruined/street_turn",
        "processors": {
          "processors": []
        },
        "projection": "terrain_matching"
      },
      "weight": 64
    },
    {
      "element": {
        "element_type": "minecraft:single_pool_element",
        "location": "landsoficaria:villages/scrubland/ruined/street_turn_half_long",
        "processors": {
          "processors": []
        },
        "projection": "terrain_matching"
      },
      "weight": 16
    },
    {
      "element": {
        "element_type": "minecraft:single_pool_element",
        "location": "landsoficaria:villages/scrubland/ruined/street_turn_half_long_left",
        "processors": {
          "processors": []
        },
        "projection": "terrain_matching"
      },
      "weight": 16
    },
    {
      "element": {
        "element_type": "minecraft:single_pool_element",
        "location": "landsoficaria:villages/scrubland/ruined/street_turn_semi",
        "processors": {
          "processors": []
        },
        "projection": "terrain_matching"
      },
      "weight": 16
    },
    {
      "element": {
        "element_type": "minecraft:single_pool_element",
        "location": "landsoficaria:villages/scrubland/ruined/street_turn_semi_left",
        "processors": {
          "processors": []
        },
        "projection": "terrain_matching"
      },
      "weight": 16
    },
    {
      "element": {
        "element_type": "minecraft:single_pool_element",
        "location": "landsoficaria:villages/scrubland/ruined/street_turn_semi_long",
        "processors": {
          "processors": []
        },
        "projection": "terrain_matching"
      },
      "weight": 16
    },
    {
      "element": {
        "element_type": "minecraft:single_pool_element",
        "location": "landsoficaria:villages/scrubland/ruined/street_turn_semi_long_left",
        "processors": {
          "processors": []
        },
        "projection": "terrain_matching"
      },
      "weight": 16
    }
  ],
  "fallback": "minecraft:empty"
}