{
  "elements": [
    {
      "element": {
        "element_type": "minecraft:single_pool_element",
        "location": "landsoficaria:ruin/street/street",
        "processors": {
          "processors": []
        },
        "projection": "rigid"
      },
      "weight": 1
    },
    {
      "element": {
        "element_type": "minecraft:single_pool_element",
        "location": "landsoficaria:ruin/street/street_turn",
        "processors": {
          "processors": []
        },
        "projection": "rigid"
      },
      "weight": 1
    },
    {
      "element": {
        "element_type": "minecraft:single_pool_element",
        "location": "landsoficaria:ruin/street/street_turn_half_long",
        "processors": {
          "processors": []
        },
        "projection": "rigid"
      },
      "weight": 1
    },
    {
      "element": {
        "element_type": "minecraft:single_pool_element",
        "location": "landsoficaria:ruin/street/street_turn_half_long_left",
        "processors": {
          "processors": []
        },
        "projection": "rigid"
      },
      "weight": 1
    },
    {
      "element": {
        "element_type": "minecraft:single_pool_element",
        "location": "landsoficaria:ruin/street/street_turn_semi",
        "processors": {
          "processors": []
        },
        "projection": "rigid"
      },
      "weight": 1
    },
    {
      "element": {
        "element_type": "minecraft:single_pool_element",
        "location": "landsoficaria:ruin/street/street_turn_semi_left",
        "processors": {
          "processors": []
        },
        "projection": "rigid"
      },
      "weight": 1
    },
    {
      "element": {
        "element_type": "minecraft:single_pool_element",
        "location": "landsoficaria:ruin/street/street_turn_semi_long",
        "processors": {
          "processors": []
        },
        "projection": "rigid"
      },
      "weight": 1
    },
    {
      "element": {
        "element_type": "minecraft:single_pool_element",
        "location": "landsoficaria:ruin/street/street_turn_semi_long_left",
        "processors": {
          "processors": []
        },
        "projection": "rigid"
      },
      "weight": 1
    }
  ],
  "fallback": "minecraft:empty"
}