{
  "parent": "minecraft:recipes/root",
  "criteria": {
    "has_landsoficaria:marl_adobe": {
      "conditions": {
        "items": [
          {
            "items": [
              "landsoficaria:marl_adobe"
            ]
          }
        ]
      },
      "trigger": "minecraft:inventory_changed"
    },
    "has_the_recipe": {
      "conditions": {
        "recipe": "landsoficaria:marl_adobe_slab"
      },
      "trigger": "minecraft:recipe_unlocked"
    }
  },
  "requirements": [
    [
      "has_the_recipe",
      "has_landsoficaria:marl_adobe"
    ]
  ],
  "rewards": {
    "recipes": [
      "landsoficaria:marl_adobe_slab"
    ]
  },
  "sends_telemetry_event": false
}