{
  "processors": [
    {
      "processor_type": "minecraft:rule",
      "rules": [
        {
          "input_predicate": {
            "block": "minecraft:chiseled_bookshelf",
            "predicate_type": "minecraft:block_match"
          },
          "location_predicate": {
            "predicate_type": "minecraft:always_true"
          },
          "output_state": {
            "Name": "minecraft:air"
          }
        }
      ]
    },
    {
      "processor_type": "minecraft:rule",
      "rules": [
        {
          "input_predicate": {
            "block": "minecraft:composter",
            "predicate_type": "minecraft:block_match"
          },
          "location_predicate": {
            "predicate_type": "minecraft:always_true"
          },
          "output_state": {
            "Name": "minecraft:air"
          }
        }
      ]
    },
    {
      "processor_type": "minecraft:rule",
      "rules": [
        {
          "input_predicate": {
            "block": "minecraft:gray_concrete",
            "predicate_type": "minecraft:block_match"
          },
          "location_predicate": {
            "predicate_type": "minecraft:always_true"
          },
          "output_state": {
            "Name": "minecraft:air"
          }
        }
      ]
    },
    {
      "processor_type": "minecraft:rule",
      "rules": [
        {
          "input_predicate": {
            "block": "minecraft:pink_concrete",
            "predicate_type": "minecraft:block_match"
          },
          "location_predicate": {
            "predicate_type": "minecraft:always_true"
          },
          "output_state": {
            "Name": "minecraft:air"
          }
        }
      ]
    },
    {
      "processor_type": "minecraft:rule",
      "rules": [
        {
          "input_predicate": {
            "block": "landsoficaria:surface_lignite",
            "predicate_type": "minecraft:block_match"
          },
          "location_predicate": {
            "predicate_type": "minecraft:always_true"
          },
          "output_state": {
            "Name": "minecraft:air"
          }
        }
      ]
    },
    {
      "processor_type": "minecraft:rule",
      "rules": [
        {
          "input_predicate": {
            "block": "landsoficaria:grainite_bricks",
            "predicate_type": "minecraft:block_match"
          },
          "location_predicate": {
            "predicate_type": "minecraft:always_true"
          },
          "output_state": {
            "Name": "minecraft:air"
          }
        }
      ]
    },
    {
      "processor_type": "minecraft:rule",
      "rules": [
        {
          "input_predicate": {
            "block": "landsoficaria:grainite_brick_stairs",
            "predicate_type": "minecraft:block_match"
          },
          "location_predicate": {
            "predicate_type": "minecraft:always_true"
          },
          "output_state": {
            "Name": "minecraft:air"
          }
        }
      ]
    },
    {
      "processor_type": "minecraft:rule",
      "rules": [
        {
          "input_predicate": {
            "block": "landsoficaria:yellowstone_adobe",
            "predicate_type": "minecraft:block_match"
          },
          "location_predicate": {
            "predicate_type": "minecraft:always_true"
          },
          "output_state": {
            "Name": "landsoficaria:sunstone_adobe"
          }
        }
      ]
    },
    {
      "processor_type": "minecraft:rule",
      "rules": [
        {
          "input_predicate": {
            "block": "landsoficaria:yellowstone_adobe_stairs",
            "predicate_type": "minecraft:block_match"
          },
          "location_predicate": {
            "predicate_type": "minecraft:always_true"
          },
          "output_state": {
            "Name": "minecraft:air"
          }
        }
      ]
    },
    {
      "processor_type": "minecraft:rule",
      "rules": [
        {
          "input_predicate": {
            "block": "landsoficaria:yellowstone_adobe_slab",
            "predicate_type": "minecraft:block_match"
          },
          "location_predicate": {
            "predicate_type": "minecraft:always_true"
          },
          "output_state": {
            "Name": "minecraft:air"
          }
        }
      ]
    },
    {
      "processor_type": "minecraft:rule",
      "rules": [
        {
          "input_predicate": {
            "block_state": {
              "Name": "landsoficaria:sunstone_adobe"
            },
            "predicate_type": "minecraft:random_blockstate_match",
            "probability": 0.25
          },
          "location_predicate": {
            "predicate_type": "minecraft:always_true"
          },
          "output_state": {
            "Name": "minecraft:cobweb"
          },
          "position_predicate": {
            "axis": "y",
            "max_chance": 1.0,
            "max_dist": 8,
            "min_chance": 0.0,
            "min_dist": 0,
            "predicate_type": "minecraft:axis_aligned_linear_pos"
          }
        },
        {
          "input_predicate": {
            "block_state": {
              "Name": "landsoficaria:sunstone_adobe"
            },
            "predicate_type": "minecraft:random_blockstate_match",
            "probability": 0.25
          },
          "location_predicate": {
            "predicate_type": "minecraft:always_true"
          },
          "output_state": {
            "Name": "minecraft:air"
          },
          "position_predicate": {
            "axis": "y",
            "max_chance": 1.0,
            "max_dist": 8,
            "min_chance": 0.0,
            "min_dist": 0,
            "predicate_type": "minecraft:axis_aligned_linear_pos"
          }
        }
      ]
    },
    {
      "processor_type": "minecraft:rule",
      "rules": [
        {
          "input_predicate": {
            "block_state": {
              "Name": "landsoficaria:relicstone_tiles"
            },
            "predicate_type": "minecraft:random_blockstate_match",
            "probability": 0.25
          },
          "location_predicate": {
            "predicate_type": "minecraft:always_true"
          },
          "output_state": {
            "Name": "minecraft:cobweb"
          },
          "position_predicate": {
            "axis": "y",
            "max_chance": 1.0,
            "max_dist": 8,
            "min_chance": 0.0,
            "min_dist": 0,
            "predicate_type": "minecraft:axis_aligned_linear_pos"
          }
        },
        {
          "input_predicate": {
            "block_state": {
              "Name": "landsoficaria:relicstone_tiles"
            },
            "predicate_type": "minecraft:random_blockstate_match",
            "probability": 0.25
          },
          "location_predicate": {
            "predicate_type": "minecraft:always_true"
          },
          "output_state": {
            "Name": "minecraft:air"
          },
          "position_predicate": {
            "axis": "y",
            "max_chance": 1.0,
            "max_dist": 8,
            "min_chance": 0.0,
            "min_dist": 0,
            "predicate_type": "minecraft:axis_aligned_linear_pos"
          }
        }
      ]
    },
    {
      "processor_type": "minecraft:rule",
      "rules": [
        {
          "input_predicate": {
            "block_state": {
              "Name": "landsoficaria:relicstone_tiles"
            },
            "predicate_type": "minecraft:random_blockstate_match",
            "probability": 0.5
          },
          "location_predicate": {
            "predicate_type": "minecraft:always_true"
          },
          "output_state": {
            "Name": "landsoficaria:cracked_relicstone_tiles"
          }
        },
        {
          "input_predicate": {
            "block_state": {
              "Name": "landsoficaria:relicstone_tiles"
            },
            "predicate_type": "minecraft:random_blockstate_match",
            "probability": 0.5
          },
          "location_predicate": {
            "predicate_type": "minecraft:always_true"
          },
          "output_state": {
            "Name": "landsoficaria:mossy_relicstone_tiles"
          }
        }
      ]
    },
    {
      "processor_type": "minecraft:rule",
      "rules": [
        {
          "input_predicate": {
            "block": "landsoficaria:relicstone_tile_stairs",
            "predicate_type": "minecraft:block_match"
          },
          "location_predicate": {
            "predicate_type": "minecraft:always_true"
          },
          "output_state": {
            "Name": "minecraft:air"
          }
        }
      ]
    },
    {
      "processor_type": "minecraft:rule",
      "rules": [
        {
          "input_predicate": {
            "block": "landsoficaria:chest",
            "predicate_type": "minecraft:block_match"
          },
          "location_predicate": {
            "predicate_type": "minecraft:always_true"
          },
          "output_state": {
            "Name": "minecraft:air"
          }
        }
      ]
    },
    {
      "processor_type": "minecraft:rule",
      "rules": [
        {
          "input_predicate": {
            "block_state": {
              "Name": "landsoficaria:red_loot_vase",
              "Properties": {
                "mediterranean_waterlogged": "false",
                "waterlogged": "false"
              }
            },
            "predicate_type": "minecraft:random_blockstate_match",
            "probability": 0.25
          },
          "location_predicate": {
            "predicate_type": "minecraft:always_true"
          },
          "output_state": {
            "Name": "landsoficaria:arachne_spawner"
          }
        },
        {
          "input_predicate": {
            "block_state": {
              "Name": "landsoficaria:red_loot_vase",
              "Properties": {
                "mediterranean_waterlogged": "false",
                "waterlogged": "false"
              }
            },
            "predicate_type": "minecraft:random_blockstate_match",
            "probability": 0.5
          },
          "location_predicate": {
            "predicate_type": "minecraft:always_true"
          },
          "output_state": {
            "Name": "minecraft:air"
          }
        }
      ]
    },
    {
      "processor_type": "minecraft:rule",
      "rules": [
        {
          "input_predicate": {
            "block": "landsoficaria:stripped_laurel_log",
            "predicate_type": "minecraft:block_match"
          },
          "location_predicate": {
            "predicate_type": "minecraft:always_true"
          },
          "output_state": {
            "Name": "minecraft:air"
          }
        }
      ]
    },
    {
      "processor_type": "minecraft:rule",
      "rules": [
        {
          "input_predicate": {
            "block": "landsoficaria:laurel_stairs",
            "predicate_type": "minecraft:block_match"
          },
          "location_predicate": {
            "predicate_type": "minecraft:always_true"
          },
          "output_state": {
            "Name": "minecraft:air"
          }
        }
      ]
    },
    {
      "processor_type": "minecraft:rule",
      "rules": [
        {
          "input_predicate": {
            "block": "landsoficaria:laurel_slab",
            "predicate_type": "minecraft:block_match"
          },
          "location_predicate": {
            "predicate_type": "minecraft:always_true"
          },
          "output_state": {
            "Name": "minecraft:air"
          }
        }
      ]
    },
    {
      "processor_type": "minecraft:rule",
      "rules": [
        {
          "input_predicate": {
            "block": "landsoficaria:simple_laurel_rack",
            "predicate_type": "minecraft:block_match"
          },
          "location_predicate": {
            "predicate_type": "minecraft:always_true"
          },
          "output_state": {
            "Name": "minecraft:air"
          }
        }
      ]
    },
    {
      "processor_type": "minecraft:rule",
      "rules": [
        {
          "input_predicate": {
            "block": "landsoficaria:laurel_rack",
            "predicate_type": "minecraft:block_match"
          },
          "location_predicate": {
            "predicate_type": "minecraft:always_true"
          },
          "output_state": {
            "Name": "minecraft:air"
          }
        }
      ]
    },
    {
      "processor_type": "minecraft:rule",
      "rules": [
        {
          "input_predicate": {
            "block": "landsoficaria:laurel_barrel",
            "predicate_type": "minecraft:block_match"
          },
          "location_predicate": {
            "predicate_type": "minecraft:always_true"
          },
          "output_state": {
            "Name": "minecraft:air"
          }
        }
      ]
    },
    {
      "processor_type": "minecraft:rule",
      "rules": [
        {
          "input_predicate": {
            "block": "landsoficaria:loaded_laurel_barrel",
            "predicate_type": "minecraft:block_match"
          },
          "location_predicate": {
            "predicate_type": "minecraft:always_true"
          },
          "output_state": {
            "Name": "minecraft:air"
          }
        }
      ]
    },
    {
      "processor_type": "minecraft:rule",
      "rules": [
        {
          "input_predicate": {
            "block": "landsoficaria:tapped_laurel_barrel",
            "predicate_type": "minecraft:block_match"
          },
          "location_predicate": {
            "predicate_type": "minecraft:always_true"
          },
          "output_state": {
            "Name": "minecraft:air"
          }
        }
      ]
    },
    {
      "processor_type": "minecraft:rule",
      "rules": [
        {
          "input_predicate": {
            "block": "landsoficaria:triple_laurel_barrel_rack",
            "predicate_type": "minecraft:block_match"
          },
          "location_predicate": {
            "predicate_type": "minecraft:always_true"
          },
          "output_state": {
            "Name": "minecraft:air"
          }
        }
      ]
    },
    {
      "processor_type": "minecraft:rule",
      "rules": [
        {
          "input_predicate": {
            "block": "landsoficaria:laurel_wall_sign",
            "predicate_type": "minecraft:block_match"
          },
          "location_predicate": {
            "predicate_type": "minecraft:always_true"
          },
          "output_state": {
            "Name": "minecraft:air"
          }
        }
      ]
    },
    {
      "processor_type": "minecraft:rule",
      "rules": [
        {
          "input_predicate": {
            "block": "landsoficaria:plane_planks",
            "predicate_type": "minecraft:block_match"
          },
          "location_predicate": {
            "predicate_type": "minecraft:always_true"
          },
          "output_state": {
            "Name": "minecraft:air"
          }
        }
      ]
    },
    {
      "processor_type": "minecraft:rule",
      "rules": [
        {
          "input_predicate": {
            "block": "landsoficaria:plane_slab",
            "predicate_type": "minecraft:block_match"
          },
          "location_predicate": {
            "predicate_type": "minecraft:always_true"
          },
          "output_state": {
            "Name": "minecraft:air"
          }
        }
      ]
    },
    {
      "processor_type": "minecraft:rule",
      "rules": [
        {
          "input_predicate": {
            "block": "landsoficaria:plane_fence",
            "predicate_type": "minecraft:block_match"
          },
          "location_predicate": {
            "predicate_type": "minecraft:always_true"
          },
          "output_state": {
            "Name": "minecraft:air"
          }
        }
      ]
    },
    {
      "processor_type": "minecraft:rule",
      "rules": [
        {
          "input_predicate": {
            "block": "landsoficaria:plane_crafting_table",
            "predicate_type": "minecraft:block_match"
          },
          "location_predicate": {
            "predicate_type": "minecraft:always_true"
          },
          "output_state": {
            "Name": "minecraft:air"
          }
        }
      ]
    },
    {
      "processor_type": "minecraft:rule",
      "rules": [
        {
          "input_predicate": {
            "block": "landsoficaria:plane_door",
            "predicate_type": "minecraft:block_match"
          },
          "location_predicate": {
            "predicate_type": "minecraft:always_true"
          },
          "output_state": {
            "Name": "minecraft:air"
          }
        }
      ]
    },
    {
      "processor_type": "minecraft:rule",
      "rules": [
        {
          "input_predicate": {
            "block": "landsoficaria:plane_trapdoor",
            "predicate_type": "minecraft:block_match"
          },
          "location_predicate": {
            "predicate_type": "minecraft:always_true"
          },
          "output_state": {
            "Name": "minecraft:air"
          }
        }
      ]
    },
    {
      "processor_type": "minecraft:rule",
      "rules": [
        {
          "input_predicate": {
            "block": "landsoficaria:plane_ladder",
            "predicate_type": "minecraft:block_match"
          },
          "location_predicate": {
            "predicate_type": "minecraft:always_true"
          },
          "output_state": {
            "Name": "minecraft:air"
          }
        }
      ]
    }
  ]
}